odoo/addons/product_category_product_link/README.rst
odoo/addons/product_category_product_link/__init__.py
odoo/addons/product_category_product_link/__manifest__.py
odoo/addons/product_category_product_link/i18n/product_category_product_link.pot
odoo/addons/product_category_product_link/models/__init__.py
odoo/addons/product_category_product_link/models/product_category.py
odoo/addons/product_category_product_link/models/product_template.py
odoo/addons/product_category_product_link/readme/CONTRIBUTORS.rst
odoo/addons/product_category_product_link/readme/DESCRIPTION.rst
odoo/addons/product_category_product_link/static/description/icon.png
odoo/addons/product_category_product_link/static/description/index.html
odoo14_addon_product_category_product_link-14.0.1.0.1.dist-info/METADATA
odoo14_addon_product_category_product_link-14.0.1.0.1.dist-info/WHEEL
odoo14_addon_product_category_product_link-14.0.1.0.1.dist-info/top_level.txt
odoo14_addon_product_category_product_link-14.0.1.0.1.dist-info/RECORD
